kalman_detector/__init__.py
kalman_detector/core.py
kalman_detector/efficiency.py
kalman_detector/main.py
kalman_detector/svm.py
kalman_detector/utils.py
kalman_detector-0.5.0.dist-info/LICENSE
kalman_detector-0.5.0.dist-info/METADATA
kalman_detector-0.5.0.dist-info/WHEEL
kalman_detector-0.5.0.dist-info/top_level.txt
kalman_detector-0.5.0.dist-info/RECORD
